tagify/__init__.py
tagify/apps.py
tagify/consts.py
tagify/fields.py
tagify/models.py
tagify/widgets.py
tagify/static/tagify/css/tagify.css
tagify/static/tagify/js/tagify.min.js
tagify/static/tagify/js/tagify.polyfills.min.js
tagify/templates/tagify/tagify_input.html
django_tagify2-1.0.19.dist-info/LICENSE
django_tagify2-1.0.19.dist-info/METADATA
django_tagify2-1.0.19.dist-info/WHEEL
django_tagify2-1.0.19.dist-info/top_level.txt
django_tagify2-1.0.19.dist-info/RECORD
