Metadata-Version: 2.1
Name: django-tagify2
Version: 1.0.19
Summary: django tag input field using tagify.js
Home-page: https://github.com/gojuukaze/django-tagify2
Author: gojuukaze
Author-email: ikaze_email@163.com
License: GUN V3.0
Platform: Any
Classifier: Development Status :: 5 - Production/Stable
Classifier: Intended Audience :: Developers
Classifier: License :: OSI Approved :: GNU General Public License v3 (GPLv3)
Classifier: Operating System :: OS Independent
Classifier: Programming Language :: Python :: 3
Classifier: Programming Language :: Python :: 3.3
Classifier: Programming Language :: Python :: 3.4
Classifier: Programming Language :: Python :: 3.5
Classifier: Programming Language :: Python :: 3.6
Classifier: Framework :: Django
Classifier: Environment :: Web Environment
Requires-Python: >=3
License-File: LICENSE
